{
  "resource": "Users",
  "http_method": "POST",
  "route": "/v1/users",
  "description": "Creating new user",
  "explanation": null,
  "parameters": [
    {
      "required": true,
      "scope": "user",
      "name": "uuid",
      "description": "User oauth uuid"
    },
    {
      "required": true,
      "name": "key",
      "description": "App secret key"
    }
  ],
  "response_fields": [

  ],
  "requests": [
    {
      "request_method": "POST",
      "request_path": "/v1/users",
      "request_body": "user[uuid]=af422d9c2607&key=0c8f4e68a202",
      "request_headers": {
        "Accept": "application/json"
      },
      "request_query_parameters": {
      },
      "request_content_type": "application/x-www-form-urlencoded",
      "response_status": 201,
      "response_status_text": "Created",
      "response_body": "{\"user\":{\"uuid\":\"af422d9c2607\",\"authentication_token\":\"QrztJBK31y8Xz57LQDXC\"}}",
      "response_headers": {
        "Content-Type": "application/json; charset=utf-8"
      },
      "response_content_type": "application/json; charset=utf-8",
      "curl": "curl \"http://localhost:5000/v1/users\" -d 'user[uuid]=af422d9c2607&key=0c8f4e68a202' -X POST \\\n\t-H \"Accept: application/json\""
    }
  ]
}